capypdf-0.18.0.dist-info/METADATA
capypdf-0.18.0.dist-info/WHEEL
capypdf-0.18.0.dist-info/COPYING
.capypdf.mesonpy.libs/capypdf-0.dll
capypdf-0.18.0.data/purelib/capypdf.py
capypdf-0.18.0.dist-info/RECORD
